aijournal/__init__.py
aijournal/_version.py
aijournal/cli.py
aijournal/fakes.py
aijournal/ingest_agent.py
aijournal/py.typed
aijournal/schema.py
aijournal/api/__init__.py
aijournal/api/capture.py
aijournal/api/chat.py
aijournal/commands/__init__.py
aijournal/commands/advise.py
aijournal/commands/audit.py
aijournal/commands/chat.py
aijournal/commands/chatd.py
aijournal/commands/facts.py
aijournal/commands/index.py
aijournal/commands/ingest.py
aijournal/commands/init.py
aijournal/commands/microfacts.py
aijournal/commands/new.py
aijournal/commands/pack.py
aijournal/commands/persona.py
aijournal/commands/profile.py
aijournal/commands/profile_update.py
aijournal/commands/summarize.py
aijournal/commands/system.py
aijournal/common/__init__.py
aijournal/common/app_config.py
aijournal/common/base.py
aijournal/common/command_runner.py
aijournal/common/config_loader.py
aijournal/common/constants.py
aijournal/common/context.py
aijournal/common/logging.py
aijournal/common/meta.py
aijournal/common/types.py
aijournal/domain/__init__.py
aijournal/domain/advice.py
aijournal/domain/changes.py
aijournal/domain/chat.py
aijournal/domain/chat_sessions.py
aijournal/domain/claims.py
aijournal/domain/enums.py
aijournal/domain/events.py
aijournal/domain/evidence.py
aijournal/domain/facts.py
aijournal/domain/index.py
aijournal/domain/journal.py
aijournal/domain/packs.py
aijournal/domain/persona.py
aijournal/domain/prompts.py
aijournal/io/__init__.py
aijournal/io/artifacts.py
aijournal/io/chat_sessions.py
aijournal/io/yaml_io.py
aijournal/models/__init__.py
aijournal/models/authoritative.py
aijournal/models/base.py
aijournal/models/claim_atoms.py
aijournal/models/derived.py
aijournal/pipelines/__init__.py
aijournal/pipelines/advise.py
aijournal/pipelines/facts.py
aijournal/pipelines/index.py
aijournal/pipelines/normalization.py
aijournal/pipelines/pack.py
aijournal/pipelines/persona.py
aijournal/pipelines/profile_update.py
aijournal/pipelines/summarize.py
aijournal/services/__init__.py
aijournal-0.3.0.dist-info/METADATA
aijournal-0.3.0.dist-info/WHEEL
aijournal-0.3.0.dist-info/entry_points.txt
aijournal-0.3.0.dist-info/RECORD
