Metadata-Version: 2.4
Name: aijournal
Version: 0.3.0
Summary: Local-first, YAML-centric personal self-modeling agent
Author-email: Bas Nijholt <bas@nijho.lt>
Requires-Python: >=3.12
Requires-Dist: chromadb>=0.5.3
Requires-Dist: fastapi>=0.115.0
Requires-Dist: httpx>=0.28.1
Requires-Dist: numpy
Requires-Dist: orjson>=3.10.4
Requires-Dist: pydantic-ai>=1.6.0
Requires-Dist: pydantic>=2.12.3
Requires-Dist: python-dateutil>=2.9.0.post0
Requires-Dist: pyyaml>=6.0.3
Requires-Dist: typer>=0.20.0
Requires-Dist: uvicorn>=0.30.6
Requires-Dist: versioningit>=0.4.0
